{
  "configVersion": 1,
  "timestamp": 1695329247976,
  "index": "/loud-6-castle/index.html",
  "assetGroups": [
    {
      "name": "app",
      "installMode": "prefetch",
      "updateMode": "prefetch",
      "cacheQueryOptions": {
        "ignoreVary": true
      },
      "urls": [
        "/loud-6-castle/252.dbb42b39f59afdae.js",
        "/loud-6-castle/287.64bb45e3b0873326.js",
        "/loud-6-castle/384.616f10b3bb2e3ae9.js",
        "/loud-6-castle/479.f75cb35211a8f454.js",
        "/loud-6-castle/549.fb9e9637843b2789.js",
        "/loud-6-castle/596.9f085285dce2be07.js",
        "/loud-6-castle/732.bea8c00600e06b39.js",
        "/loud-6-castle/833.5d2869d49ae8035a.js",
        "/loud-6-castle/common.7b190f87fd0c4972.js",
        "/loud-6-castle/favicon.ico",
        "/loud-6-castle/index.html",
        "/loud-6-castle/main.c5adb2daf22fb8a4.js",
        "/loud-6-castle/manifest.webmanifest",
        "/loud-6-castle/polyfills.c780853d6f7546c3.js",
        "/loud-6-castle/runtime.b5a179cf4df93727.js",
        "/loud-6-castle/styles.08514711df6630d5.css"
      ],
      "patterns": []
    },
    {
      "name": "assets",
      "installMode": "lazy",
      "updateMode": "prefetch",
      "cacheQueryOptions": {
        "ignoreVary": true
      },
      "urls": [
        "/loud-6-castle/apple-touch-icon.png",
        "/loud-6-castle/assets/images/default-profile.png",
        "/loud-6-castle/assets/ngx-rocket-logo.png",
        "/loud-6-castle/assets/ngx-rocket-logo@192.png",
        "/loud-6-castle/fa-brands-400.5f7c5bb77eae788b.ttf",
        "/loud-6-castle/fa-brands-400.9210030c21e68a90.woff2",
        "/loud-6-castle/fa-regular-400.02ad4ff91ef84f65.woff2",
        "/loud-6-castle/fa-regular-400.570a165b064c1468.ttf",
        "/loud-6-castle/fa-solid-900.0b5caff7ad4bc179.ttf",
        "/loud-6-castle/fa-solid-900.3eae9857c06e9372.woff2"
      ],
      "patterns": []
    }
  ],
  "dataGroups": [],
  "hashTable": {
    "/loud-6-castle/252.dbb42b39f59afdae.js": "38b1b0df8dd888b79ccb8042e3de906a93c5ce31",
    "/loud-6-castle/287.64bb45e3b0873326.js": "a47a749d1bc6974dc619c029517abb260320f50b",
    "/loud-6-castle/384.616f10b3bb2e3ae9.js": "1eb7ce00e939937e4ad6fdab57f0523d4cbbae22",
    "/loud-6-castle/479.f75cb35211a8f454.js": "e07942077c46d22c6c8005b440d33fd4de0afd6a",
    "/loud-6-castle/549.fb9e9637843b2789.js": "60515de0094687dcabe8d01faf06e8b4cfe68e3d",
    "/loud-6-castle/596.9f085285dce2be07.js": "ba3ca5ce9bd0a54180cce2d1dc42daa82c21f64c",
    "/loud-6-castle/732.bea8c00600e06b39.js": "b5e126bc07313aae28289494c28820ab5ae81bcc",
    "/loud-6-castle/833.5d2869d49ae8035a.js": "ad705d6663de4e95ec18a559ab748fba191da777",
    "/loud-6-castle/apple-touch-icon.png": "229df2094cc590088de00ea97a1eb4e4493101d2",
    "/loud-6-castle/assets/images/default-profile.png": "5b087994ef03afc094eff144e97d19d15e7b23db",
    "/loud-6-castle/assets/ngx-rocket-logo.png": "0ac53fd27406fe5a36e68285315fb0012e54058e",
    "/loud-6-castle/assets/ngx-rocket-logo@192.png": "461b730f9c6dc818f8af9acbe62dfde24dc02d7a",
    "/loud-6-castle/common.7b190f87fd0c4972.js": "193fd2e6a73fc37aac4756b1bd8e3f8c76405cb3",
    "/loud-6-castle/fa-brands-400.5f7c5bb77eae788b.ttf": "f0982a77285d53653845b0a78170b4688db972f1",
    "/loud-6-castle/fa-brands-400.9210030c21e68a90.woff2": "4350f9ba93384634faf35f41c503c99c767f1069",
    "/loud-6-castle/fa-regular-400.02ad4ff91ef84f65.woff2": "fb363d27cfdfe71a243fa2ac3dab2815232b9b7e",
    "/loud-6-castle/fa-regular-400.570a165b064c1468.ttf": "67afa6237670ab99125056f2899129f22912dcf3",
    "/loud-6-castle/fa-solid-900.0b5caff7ad4bc179.ttf": "20bd663830188cbadd2264e1daf9497c3ffc3621",
    "/loud-6-castle/fa-solid-900.3eae9857c06e9372.woff2": "6b99aa650bd12a36caa14e0127435d8f4cd3ba73",
    "/loud-6-castle/favicon.ico": "b65083d46bbf63692d5d2cdd69622e6d7ecae317",
    "/loud-6-castle/index.html": "f8b70707849ed306c9262a6203af2610d1e93cab",
    "/loud-6-castle/main.c5adb2daf22fb8a4.js": "c861f4162ee5209697ad22216f604197fdde9c19",
    "/loud-6-castle/manifest.webmanifest": "8a415077cd71743f6b23f5481a96f4c8c00430ea",
    "/loud-6-castle/polyfills.c780853d6f7546c3.js": "b429ad96b62ab6f13f056dffca4a2db1d63149ca",
    "/loud-6-castle/runtime.b5a179cf4df93727.js": "90245bdd10aaa85bb57c1ec3f3f2cdc9e0fda214",
    "/loud-6-castle/styles.08514711df6630d5.css": "acf2b0e78639ada4d8f7dcb7dd369f95585d1533"
  },
  "navigationUrls": [
    {
      "positive": true,
      "regex": "^\\/.*$"
    },
    {
      "positive": false,
      "regex": "^\\/(?:.+\\/)?[^/]*\\.[^/]*$"
    },
    {
      "positive": false,
      "regex": "^\\/(?:.+\\/)?[^/]*__[^/]*$"
    },
    {
      "positive": false,
      "regex": "^\\/(?:.+\\/)?[^/]*__[^/]*\\/.*$"
    }
  ],
  "navigationRequestStrategy": "performance"
}